noahs_local_speech_recognition/__init__.py
noahs_local_speech_recognition/speech_recognizer.py
noahs_local_speech_recognition-0.1.4.dist-info/METADATA
noahs_local_speech_recognition-0.1.4.dist-info/WHEEL
noahs_local_speech_recognition-0.1.4.dist-info/top_level.txt
noahs_local_speech_recognition-0.1.4.dist-info/RECORD
