Metadata-Version: 2.4
Name: noahs_local_speech_recognition
Version: 0.1.4
Summary: Easy to use implementation of Vosk local speech recognition
Author-email: Noah Jones <jonesnoah45010@gmail.com>
License: MIT
Project-URL: GitHub, https://github.com/jonesnoah45010/local_speech_recognition
Requires-Python: >=3.9
Requires-Dist: vosk
Requires-Dist: pyaudio
Requires-Dist: requests
Requires-Dist: tqdm
